[
  { "slug": "andhra-teak", "name": "Andhra Teak", "image": "/assets/images/shades/andhra-teak.jpg" },
  { "slug": "bleached-walnut", "name": "Bleached Walnut", "image": "/assets/images/shades/bleached-wallnut.jpg" },
  { "slug": "blond-wood", "name": "Blond Wood", "image": "/assets/images/shades/blond-wood.jpg" },
  { "slug": "golden-teak", "name": "Golden Teak", "image": "/assets/images/shades/golden-teak.jpg" },
  { "slug": "oak-wood", "name": "Oak Wood", "image": "/assets/images/shades/oak-wood.jpg" },
  { "slug": "rose-wood", "name": "Rose Wood", "image": "/assets/images/shades/rose-wood.jpg" },
  { "slug": "wenge-brown", "name": "Wenge Brown", "image": "/assets/images/shades/wenge-brown.jpg" },
  { "slug": "white-satuario-marble", "name": "White Satuario Marble", "image": "/assets/images/shades/white-satuario-marble.jpg" },
  { "slug": "green-marble", "name": "Green Marble", "image": "/assets/images/shades/green-marble.jpg" },
  { "slug": "lt-grey", "name": "Light Grey", "image": "/assets/images/shades/lt-grey.jpg" },
  { "slug": "dark-grey-marble", "name": "Dark Grey Marble", "image": "/assets/images/shades/dark-grey-marble.jpg" }
]
